copernicus_eodata/__init__.py
copernicus_eodata/eodata.py
copernicus_eodata-0.0.2.dist-info/METADATA
copernicus_eodata-0.0.2.dist-info/WHEEL
copernicus_eodata-0.0.2.dist-info/licenses/LICENSE
copernicus_eodata-0.0.2.dist-info/RECORD
