Metadata-Version: 2.3
Name: copernicus_eodata
Version: 0.0.2
Summary: A minimal Copernicus Ecosystem API
Project-URL: Homepage, https://gitlab.com/SteffenME1/copernicus-eodata
Project-URL: Issues, https://gitlab.com/SteffenME1/copernicus-eodata/-/issues
Author-email: Steffen Merseburg <steffen.merseburg@space-eye.org>
License-File: LICENSE
Classifier: License :: OSI Approved :: MIT License
Classifier: Operating System :: OS Independent
Classifier: Programming Language :: Python :: 3
Requires-Python: >=3.8
